CLIScript/__init__.py
CLIScript/cli.py
CLIScript/test_utils.py
CLIScript/script/core.py
cliscript-0.1.5.dist-info/licenses/LICENSE
cliscript-0.1.5.dist-info/METADATA
cliscript-0.1.5.dist-info/WHEEL
cliscript-0.1.5.dist-info/entry_points.txt
cliscript-0.1.5.dist-info/top_level.txt
cliscript-0.1.5.dist-info/RECORD
