Metadata-Version: 2.4
Name: cliscript
Version: 0.1.5
Summary: A Domain Specific Language for building CLI applications
Home-page: https://github.com/xYuan20d/CLIScript
Author: xYuan20d
Author-email: xYuan20d <xiaoyy20d@gmail.com>
License: MIT
Project-URL: Homepage, https://github.com/xYuan20d/CLIScript
Project-URL: Bug Tracker, https://github.com/xYuan20d/CLIScript/issues
Keywords: cli,dsl,argparse,command-line,parser
Classifier: Development Status :: 3 - Alpha
Classifier: Intended Audience :: Developers
Classifier: Topic :: Software Development :: Build Tools
Classifier: License :: OSI Approved :: MIT License
Classifier: Programming Language :: Python :: 3
Classifier: Programming Language :: Python :: 3.7
Classifier: Programming Language :: Python :: 3.8
Classifier: Programming Language :: Python :: 3.9
Classifier: Programming Language :: Python :: 3.10
Classifier: Programming Language :: Python :: 3.11
Requires-Python: >=3.7
License-File: LICENSE
Dynamic: author
Dynamic: home-page
Dynamic: license-file
Dynamic: requires-python
